drok_xyt01/__init__.py
drok_xyt01/cli.py
drok_xyt01/driver.py
drok_xyt01-0.1.1.dist-info/licenses/LICENSE
drok_xyt01-0.1.1.dist-info/METADATA
drok_xyt01-0.1.1.dist-info/WHEEL
drok_xyt01-0.1.1.dist-info/entry_points.txt
drok_xyt01-0.1.1.dist-info/top_level.txt
drok_xyt01-0.1.1.dist-info/RECORD
